rocm_docs/__init__.py
rocm_docs/article_info.py
rocm_docs/core.py
rocm_docs/doxygen.py
rocm_docs/formatting.py
rocm_docs/projects.py
rocm_docs/py.typed
rocm_docs/theme.py
rocm_docs/util.py
rocm_docs/data/projects.schema.json
rocm_docs/data/projects.yaml
rocm_docs/data/_doxygen/doxygen-img-ref-fix.css
rocm_docs/data/_doxygen/extra_stylesheet.css
rocm_docs/data/_doxygen/footer.html
rocm_docs/data/_doxygen/header.html
rocm_docs/data/_doxygen/stylesheet.css
rocm_docs/rocm_docs_theme/404.html
rocm_docs/rocm_docs_theme/layout.html
rocm_docs/rocm_docs_theme/theme.conf
rocm_docs/rocm_docs_theme/components/article-info.html
rocm_docs/rocm_docs_theme/components/left-side-menu.html
rocm_docs/rocm_docs_theme/components/toggle-primary-sidebar.html
rocm_docs/rocm_docs_theme/flavors/ai-developer-hub/footer.jinja
rocm_docs/rocm_docs_theme/flavors/ai-developer-hub/header.jinja
rocm_docs/rocm_docs_theme/flavors/ai-developer-hub/left-side-menu.jinja
rocm_docs/rocm_docs_theme/flavors/amdgpu/footer.jinja
rocm_docs/rocm_docs_theme/flavors/amdgpu/header.jinja
rocm_docs/rocm_docs_theme/flavors/amdgpu/left-side-menu.jinja
rocm_docs/rocm_docs_theme/flavors/generic/footer.jinja
rocm_docs/rocm_docs_theme/flavors/generic/header.jinja
rocm_docs/rocm_docs_theme/flavors/generic/left-side-menu.jinja
rocm_docs/rocm_docs_theme/flavors/gsplat/footer.jinja
rocm_docs/rocm_docs_theme/flavors/gsplat/header.jinja
rocm_docs/rocm_docs_theme/flavors/gsplat/left-side-menu.jinja
rocm_docs/rocm_docs_theme/flavors/instinct/footer.jinja
rocm_docs/rocm_docs_theme/flavors/instinct/header.jinja
rocm_docs/rocm_docs_theme/flavors/instinct/left-side-menu.jinja
rocm_docs/rocm_docs_theme/flavors/rocm/footer.jinja
rocm_docs/rocm_docs_theme/flavors/rocm/header.jinja
rocm_docs/rocm_docs_theme/flavors/rocm/left-side-menu.jinja
rocm_docs/rocm_docs_theme/flavors/rocm/meta.jinja
rocm_docs/rocm_docs_theme/flavors/rocm-blogs/footer.jinja
rocm_docs/rocm_docs_theme/flavors/rocm-blogs/header.jinja
rocm_docs_core-1.31.3.dist-info/licenses/LICENSE.txt
rocm_docs_core-1.31.3.dist-info/METADATA
rocm_docs_core-1.31.3.dist-info/WHEEL
rocm_docs_core-1.31.3.dist-info/entry_points.txt
rocm_docs_core-1.31.3.dist-info/top_level.txt
rocm_docs_core-1.31.3.dist-info/RECORD
