Metadata-Version: 2.4
Name: rocm-docs-core
Version: 1.31.3
Summary: Core utilities for all ROCm documentation on RTD
Author-email: Lauren Wrubleski <Lauren.Wrubleski@amd.com>
Project-URL: repository, https://github.com/ROCm/rocm-docs-core
Project-URL: documentation, https://rocm.docs.amd.com
Classifier: Programming Language :: Python :: 3
Classifier: License :: OSI Approved :: MIT License
Classifier: Operating System :: OS Independent
Requires-Python: >=3.10
License-File: LICENSE.txt
Requires-Dist: GitPython>=3.1.30
Requires-Dist: PyGithub>=1.58.1
Requires-Dist: sphinx>=5.3.0
Requires-Dist: breathe>=4.34.0
Requires-Dist: myst-nb>=1.1.2
Requires-Dist: pydata-sphinx-theme>=0.15.4
Requires-Dist: sphinx-book-theme>=1.1.4
Requires-Dist: sphinx-copybutton>=0.5.1
Requires-Dist: sphinx-design>=0.3.0
Requires-Dist: sphinx_external_toc>=0.3.1
Requires-Dist: sphinx-notfound-page>=0.8.3
Requires-Dist: pyyaml>=6.0
Requires-Dist: fastjsonschema>=2.16
Provides-Extra: api-reference
Requires-Dist: doxysphinx>=3.3.2; extra == "api-reference"
Provides-Extra: development
Requires-Dist: black>=22.1; extra == "development"
Requires-Dist: build>=0.10.0; extra == "development"
Requires-Dist: commitizen>=2.42; extra == "development"
Requires-Dist: isort>=5.12.0; extra == "development"
Requires-Dist: mypy>=1.3.0; extra == "development"
Requires-Dist: pip-tools>=6.13.0; extra == "development"
Requires-Dist: pre-commit>=3.3.2; extra == "development"
Requires-Dist: pytest>=7.4.2; extra == "development"
Requires-Dist: ruff>=0.0.269; extra == "development"
Requires-Dist: sphinxcontrib.doxylink>=1.12.2; extra == "development"
Dynamic: license-file
